binarylane/api/__init__.py
binarylane/api/accounts/__init__.py
binarylane/api/accounts/get_v2_account.py
binarylane/api/actions/__init__.py
binarylane/api/actions/get_v2_actions.py
binarylane/api/actions/get_v2_actions_action_id.py
binarylane/api/actions/post_v2_actions_action_id_proceed.py
binarylane/api/customers/__init__.py
binarylane/api/customers/get_v2_customers_my_balance.py
binarylane/api/customers/get_v2_customers_my_invoices.py
binarylane/api/customers/get_v2_customers_my_invoices_invoice_id.py
binarylane/api/customers/get_v2_customers_my_unpaid_payment_failed_invoices.py
binarylane/api/data_usages/__init__.py
binarylane/api/data_usages/get_v2_data_usages_current.py
binarylane/api/data_usages/get_v2_data_usages_server_id_current.py
binarylane/api/domains/__init__.py
binarylane/api/domains/delete_v2_domains_domain_name.py
binarylane/api/domains/delete_v2_domains_domain_name_records_record_id.py
binarylane/api/domains/get_v2_domains.py
binarylane/api/domains/get_v2_domains_domain_name.py
binarylane/api/domains/get_v2_domains_domain_name_records.py
binarylane/api/domains/get_v2_domains_domain_name_records_record_id.py
binarylane/api/domains/get_v2_domains_nameservers.py
binarylane/api/domains/post_v2_domains.py
binarylane/api/domains/post_v2_domains_domain_name_records.py
binarylane/api/domains/post_v2_domains_refresh_nameserver_cache.py
binarylane/api/domains/put_v2_domains_domain_name_records_record_id.py
binarylane/api/images/__init__.py
binarylane/api/images/get_v2_images.py
binarylane/api/images/get_v2_images_image_id_download.py
binarylane/api/images/get_v2_images_image_id_or_slug.py
binarylane/api/images/put_v2_images_image_id.py
binarylane/api/keys/__init__.py
binarylane/api/keys/delete_v2_account_keys_key_id.py
binarylane/api/keys/get_v2_account_keys.py
binarylane/api/keys/get_v2_account_keys_key_id.py
binarylane/api/keys/post_v2_account_keys.py
binarylane/api/keys/put_v2_account_keys_key_id.py
binarylane/api/load_balancers/__init__.py
binarylane_cli-0.20.1.dist-info/LICENSE
binarylane_cli-0.20.1.dist-info/METADATA
binarylane_cli-0.20.1.dist-info/WHEEL
binarylane_cli-0.20.1.dist-info/entry_points.txt
binarylane_cli-0.20.1.dist-info/RECORD
