Metadata-Version: 2.1
Name: binarylane-cli
Version: 0.20.1
Summary: 
Author: Nathan O'Sullivan
Author-email: nathan.osullivan@mammoth.com.au
Requires-Python: >=3.8.1,<4.0.0
Classifier: Programming Language :: Python :: 3
Classifier: Programming Language :: Python :: 3.9
Classifier: Programming Language :: Python :: 3.10
Classifier: Programming Language :: Python :: 3.11
Classifier: Programming Language :: Python :: 3.12
Classifier: Programming Language :: Python :: 3.13
Requires-Dist: attrs (>=22.2.0,<23.0.0)
Requires-Dist: httpx (>=0.25.0,<0.26.0)
Requires-Dist: python-dateutil (>=2.8.2,<3.0.0)
Requires-Dist: terminaltables (>=3.1.10,<4.0.0)
